{"name":"燕庄小磨香油",
	"brand":"燕庄",
	"code":"5101009995000021",
	"productionDate":"2016.07.05",
	"Qualitydate":"15个月",
	"Authentication":"5101009990006",
	"productionAdd":{"Distribution":"安徽燕庄油脂有限责任公司",
					"households":"安徽燕庄油脂有限责任公司",
					"code":"74954234",
					"date":"2016.07.19",
					"addinfo":"12012458978964211497",
					"forminfo":"安徽省巢湖市古韶关芝麻油生产基地"},
	"logistics":{"Distribution":"成都崇信商贸物流配送公司",
					"person1":"李师傅",
					"phone1":"189****7815",
					"carcode":"川A 879Q1",
					"carperson":"李师傅",
					"cardate":"2016.07.24",
					"carnum":"7"},
	"sell":{"Retailer":"成都源溯优品科技有限公司",
					"households":"成都源溯优品科技有限公司",
					"date":"2016.07.28","code":"7"},
	"store":{"name":"安徽燕庄油脂有限责任公司",
					"person":"刘燕",
					"phone":"186****1255",
					"addr":"安徽省合肥市肥东县新城开发区"},
	"imgurl":"lib/img/cdimg/燕庄芝麻油.jpg"	
}