{
	"description": "项目配置文件。",
	"setting": {
		"urlCheck": true,
		"es6": true,
		"postcss": true,
		"minified": true,
		"newFeature": true
	},
	"compileType": "miniprogram",
	"libVersion": "1.6.4",
	"appid": "wx9f4368caa4218285",
	"projectname": "%E4%BD%9C%E4%B8%9A%E6%9C%AC005",
	"condition": {
		"search": {
			"current": -1,
			"list": []
		},
		"conversation": {
			"current": -1,
			"list": []
		},
		"plugin": {
			"current": -1,
			"list": []
		},
		"game": {
			"current": -1,
			"list": []
		},
		"miniprogram": {
			"current": -1,
			"list": [
				{
					"id": 0,
					"name": "齐慧强002班群进入",
					"pathName": "example/notice/notice",
					"query": "name=wocao",
					"scene": "1044",
					"shareInfo": {
						"groupName": "测试模拟群2",
						"shareName": "xaPJAD_68mN3KMrK7kxYh_W2fwmC0oXHq_tDTFwBEkI@cr4dev",
						"shareKey": "p_Zbk1QGfvyqfsR5TYp-9qEQC9H-LdrPeqZkH0BLlb9GRO1UUSmlf8Zkh_8zga_RMZHpROjRIhJ2TmRpZnNobw~~"
					}
				},
				{
					"id": 1,
					"name": "从齐慧强001班的群进入",
					"pathName": "example/notice/notice",
					"query": "name=wocao",
					"scene": "1044",
					"shareInfo": {
						"groupName": "测试模拟群1",
						"shareName": "xaPJAD_68mN3KMrK7kxYh0EzYeoEq-CRCMJklTi7ZBY@cr4dev",
						"shareKey": "_1bPQAMdaqwjoVmXt5njGKgfLJSKsHchaQ6_8zHYFFZ-jP0rWwdo0g-9U7Daij4ADLjW5tR4SLkCAFJx2CerWg~~"
					}
				},
				{
					"id": -1,
					"name": "从齐慧强003班的群进入",
					"pathName": "example/notice/notice",
					"query": "name=wocao",
					"scene": "1044",
					"shareInfo": {
						"groupName": "测试模拟群3",
						"shareName": "xaPJAD_68mN3KMrK7kxYh5rXskWVG7NCUHaC0UG36e8@cr4dev",
						"shareKey": "perRVYkLZTSvOb6lO5KAR8EOoKp560Pn8dM94L8NFGl-J8sU1PM3EOrYjYPWpPyKd41JBIt4dyBl9AV2f3U3HA~~"
					}
				},
				{
					"id": 3,
					"name": "通过齐慧强001群进入然后判断还没有绑定老师或者学生角色",
					"pathName": "example/bind/bind",
					"query": "cid=5a0fa4041555f04737a54407&gid=tGfSwJ0eFQyAe5hcMBFMfNpacCd5A",
					"scene": "1044",
					"shareInfo": {
						"groupName": "测试模拟群2",
						"shareName": "xaPJAD_68mN3KMrK7kxYh_W2fwmC0oXHq_tDTFwBEkI@cr4dev",
						"shareKey": "p_Zbk1QGfvyqfsR5TYp-9qEQC9H-LdrPeqZkH0BLlb9GRO1UUSmlf8Zkh_8zga_RMZHpROjRIhJ2TmRpZnNobw~~"
					}
				},
				{
					"id": -1,
					"name": "通过齐慧强002群进入然后判断还没有绑定老师或者学生角色",
					"pathName": "example/bind/bind",
					"query": "cid=5a0fa880a4759ed338434cd3&gid=tGfSwJ0Xc-Npksi_JP1dvgdk86ru0",
					"scene": "1044",
					"shareInfo": {
						"groupName": "测试模拟群2",
						"shareName": "xaPJAD_68mN3KMrK7kxYh_W2fwmC0oXHq_tDTFwBEkI@cr4dev",
						"shareKey": "p_Zbk1QGfvyqfsR5TYp-9qEQC9H-LdrPeqZkH0BLlb9GRO1UUSmlf8Zkh_8zga_RMZHpROjRIhJ2TmRpZnNobw~~"
					}
				},
				{
					"id": -1,
					"name": "创建班级",
					"pathName": "example/createclass/createclass",
					"query": "",
					"scene": "1044",
					"shareInfo": {
						"groupName": "测试模拟群2",
						"shareName": "xaPJAD_68mN3KMrK7kxYh_W2fwmC0oXHq_tDTFwBEkI@cr4dev",
						"shareKey": "p_Zbk1QGfvyqfsR5TYp-9qEQC9H-LdrPeqZkH0BLlb9GRO1UUSmlf8Zkh_8zga_RMZHpROjRIhJ2TmRpZnNobw~~"
					}
				},
				{
					"id": 6,
					"name": "从分享页面进入",
					"pathName": "example/share/share",
					"query": "notify_ids=5a1582821ca1f18b070cef5c@5a1582811ca1f18b070cef5b"
				},
				{
					"id": -1,
					"name": "more的页面",
					"pathName": "example/more/more",
					"query": "name=wocao",
					"scene": "1044",
					"shareInfo": {
						"groupName": "测试模拟群2",
						"shareName": "xaPJAD_68mN3KMrK7kxYh_W2fwmC0oXHq_tDTFwBEkI@cr4dev",
						"shareKey": "p_Zbk1QGfvyqfsR5TYp-9qEQC9H-LdrPeqZkH0BLlb9GRO1UUSmlf8Zkh_8zga_RMZHpROjRIhJ2TmRpZnNobw~~"
					}
				},
				{
					"id": -1,
					"name": "创建班级",
					"pathName": "example/createclass/createclass",
					"query": ""
				},
				{
					"id": 9,
					"name": "导入名单",
					"pathName": "example/studentadd/studentadd",
					"query": "cid=5a1ca407635ce4745c60a128&unique_code=1FrjOH&class_name=齐慧强005班"
				},
				{
					"id": -1,
					"name": "官网",
					"pathName": "example/index",
					"query": "cid=5a1ca407635ce4745c60a128&unique_code=1FrjOH&class_name=齐慧强005班"
				},
				{
					"id": -1,
					"name": "布置作业成功的提示",
					"pathName": "example/share/share",
					"query": "notify_ids=5a23cccbe211f3d57a29d206@5a23cccbe211f3d57a29d205"
				},
				{
					"id": 12,
					"name": "从qihuiqiang001群进入",
					"pathName": "example/bind/bind",
					"query": "cid=5a2499e5decec3d57491baf5",
					"scene": "1044",
					"shareInfo": {
						"groupName": "测试模拟群2",
						"shareName": "xaPJAD_68mN3KMrK7kxYh_W2fwmC0oXHq_tDTFwBEkI@cr4dev",
						"shareKey": "qkHTQc5rYpEE5XmQa44ELmOyu6oyfHIY_rTwnCYipEtiGxyA-QcGJbt_Qa3NjvNOq0I70MZqB43JT65wkpkQnA~~"
					}
				},
				{
					"id": 13,
					"name": "作业详情",
					"pathName": "example/notify/notify",
					"query": "cid=5a272fc31d95e8f26ce90acc&_id=5a2ca87dd791008b0ce8fb0f"
				},
				{
					"id": 14,
					"name": "添加导入学生的页面",
					"pathName": "example/studentadd/studentadd",
					"query": "class_name=齐慧强001班&cid=5a38d1e99b90a39137afecce&unique_code=ZqRFux"
				},
				{
					"id": 15,
					"name": "授权页面",
					"pathName": "example/auth/auth",
					"query": "member_id=5a3a040530feed3962c792f7"
				},
				{
					"id": 16,
					"name": "作业成功后的分享",
					"pathName": "example/share/share",
					"query": "notify_ids=5ac793f07eb2766b7fdfe789"
				},
				{
					"id": -1,
					"name": "创建班级成功的提示",
					"pathName": "example/notice/notice",
					"query": "class_name=齐慧强001班&cid=5a4ed1fb0e76731b4df2e7d9&unique_code=ZqRFux"
				},
				{
					"id": -1,
					"name": "创建班级成功的提示",
					"pathName": "example/importmode/importmode",
					"query": "cid=5a766c666373365c3feb9f79"
				},
				{
					"id": -1,
					"name": "分享班级",
					"pathName": "example/notice/notice",
					"query": "cid=5a9d4d2ebd78fff14dbb3fd2"
				},
				{
					"id": -1,
					"name": "创建班级成功提示",
					"pathName": "example/notice/notice",
					"query": "cid=5a9fe462f2c2ab1575f58e91"
				},
				{
					"id": -1,
					"name": "创建班级成功提示",
					"pathName": "example/notici/notice",
					"query": "cid=5a9fe462f2c2ab1575f58e91"
				},
				{
					"id": -1,
					"name": "班级已经创建提示",
					"pathName": "example/classbindedtip/classbindedtip",
					"query": "gid=GWRkU0Yy2w5QKJO6KX3kg4OazwjE"
				},
				{
					"id": -1,
					"name": "老师主页",
					"pathName": "example/main/main",
					"query": ""
				}
			]
		}
	}
}